zksnake-0.1.0.dist-info/METADATA
zksnake-0.1.0.dist-info/WHEEL
zksnake-0.1.0.dist-info/licenses/LICENSE.txt
zksnake/polynomial.py
zksnake/__init__.py
zksnake/array.py
zksnake/subprotocol/sumcheck.py
zksnake/subprotocol/__init__.py
zksnake/subprotocol/bulletproofs/range_proof.py
zksnake/subprotocol/bulletproofs/__init__.py
zksnake/subprotocol/bulletproofs/ipa.py
zksnake/subprotocol/gkr.py
zksnake/ecc.py
zksnake/constant.py
zksnake/arithmetization/__init__.py
zksnake/arithmetization/plonkish.py
zksnake/arithmetization/r1cs.py
zksnake/arithmetization/layered_circuit.py
zksnake/transcript.py
zksnake/parser.py
zksnake/plonk/__init__.py
zksnake/plonk/serialization.py
zksnake/plonk/protocol.py
zksnake/utils.py
zksnake/groth16/qap.py
zksnake/groth16/__init__.py
zksnake/groth16/serialization.py
zksnake/groth16/protocol.py
zksnake/_algebra.cpython-311-s390x-linux-gnu.so
zksnake-0.1.0.dist-info/RECORD
