Metadata-Version: 2.4
Name: zksnake
Version: 0.1.0
Classifier: Development Status :: 3 - Alpha
Classifier: Programming Language :: Python
Classifier: Intended Audience :: Science/Research
Classifier: Topic :: Security :: Cryptography
Requires-Dist: joblib>=1.4.0
Requires-Dist: pytest>=8.2.0 ; extra == 'dev'
Provides-Extra: dev
License-File: LICENSE.txt
Summary: zkSNARKs in Python
Keywords: cryptography,zksnark,zkp,r1cs,zk-snarks
Author-email: Merricx <imam@merri.cx>
Maintainer-email: Merricx <imam@merri.cx>
Requires-Python: >=3.9
Project-URL: Homepage, https://github.com/merricx/zksnake
Project-URL: Repository, https://github.com/merricx/zksnake.git
Project-URL: Bug Tracker, https://github.com/merricx/zksnake/issues
